bounded_priority_queue.py
kdtree.py
kdtree-0.15.dist-info/DESCRIPTION.rst
kdtree-0.15.dist-info/METADATA
kdtree-0.15.dist-info/RECORD
kdtree-0.15.dist-info/WHEEL
kdtree-0.15.dist-info/metadata.json
kdtree-0.15.dist-info/top_level.txt
